{
	"configurations" : 
	[
		{
			"directories" : 
			[
				{
					"build" : ".",
					"childIndexes" : 
					[
						1
					],
					"jsonFile" : "directory-.-Debug-d0094a50bb2071803777.json",
					"minimumCMakeVersion" : 
					{
						"string" : "3.8"
					},
					"projectIndex" : 0,
					"source" : "."
				},
				{
					"build" : "CMakeHelloWorld",
					"jsonFile" : "directory-CMakeHelloWorld-Debug-24c7c0af902902075b4d.json",
					"minimumCMakeVersion" : 
					{
						"string" : "3.8"
					},
					"parentIndex" : 0,
					"projectIndex" : 0,
					"source" : "CMakeHelloWorld",
					"targetIndexes" : 
					[
						0
					]
				}
			],
			"name" : "Debug",
			"projects" : 
			[
				{
					"directoryIndexes" : 
					[
						0,
						1
					],
					"name" : "CMakeHelloWorld",
					"targetIndexes" : 
					[
						0
					]
				}
			],
			"targets" : 
			[
				{
					"directoryIndex" : 1,
					"id" : "CMakeHelloWorld::@ff77643d84ae3add6701",
					"jsonFile" : "target-CMakeHelloWorld-Debug-c52bc95b127b13662962.json",
					"name" : "CMakeHelloWorld",
					"projectIndex" : 0
				}
			]
		}
	],
	"kind" : "codemodel",
	"paths" : 
	{
		"build" : "D:/git/CMakeHelloWorld/CMakeHelloWorld/out/build/x64-debug",
		"source" : "D:/git/CMakeHelloWorld/CMakeHelloWorld"
	},
	"version" : 
	{
		"major" : 2,
		"minor" : 4
	}
}
